DustCli/__init__.py
DustCli/cli/__init__.py
DustCli/cli/bootstrap.py
DustCli/cli/main.py
DustCli/cli/controllers/__init__.py
DustCli/cli/controllers/base.py
DustCli/cli/controllers/ci.py
DustCli/cli/controllers/lint.py
DustCli/cli/controllers/mr.py
DustCli/cli/controllers/package.py
DustCli/cli/controllers/project.py
DustCli/cli/controllers/publish.py
DustCli/cli/ext/__init__.py
DustCli/cli/plugins/__init__.py
DustCli/cli/plugins/example.py
DustCli/cli/templates/__init__.py
DustCli/core/__init__.py
DustCli/core/bundle.py
DustCli/core/exc.py
DustCli/core/generator.py
DustCli/core/merge.py
DustCli/utils/__init__.py
DustCli/utils/api_client.py
DustCli/utils/arg_parser.py
DustCli/utils/dust_exec.py
DustCli/utils/git.py
DustCli/utils/git_token.py
DustCli/utils/service.py
DustCli/utils/templates.py
DustCli/utils/test.py
DustCli/utils/traceid_lint.py
DustCli/utils/updater.py
DustCli/utils/version.py
DustCli/utils/version_cls.py
DustCli/utils/xcode.py
DustCli-0.6.0.dist-info/DESCRIPTION.rst
DustCli-0.6.0.dist-info/METADATA
DustCli-0.6.0.dist-info/RECORD
DustCli-0.6.0.dist-info/WHEEL
DustCli-0.6.0.dist-info/entry_points.txt
DustCli-0.6.0.dist-info/metadata.json
DustCli-0.6.0.dist-info/namespace_packages.txt
DustCli-0.6.0.dist-info/top_level.txt
tests/cli/__init__.py
tests/cli/test_DustCli.py
tests/cli/ext/__init__.py
tests/cli/plugins/__init__.py
tests/cli/plugins/test_example.py
tests/core/__init__.py
tests/core/test_exc.py
