Metadata-Version: 2.0
Name: DustCli
Version: 0.6.0
Summary: dust cli
Home-page: https://tangeche.com
Author: shaotianchi
Author-email: shaotianchi@souche.com
License: MIT
Platform: UNKNOWN
Requires-Dist: cement
Requires-Dist: pbxproj
Requires-Dist: colorlog
Requires-Dist: requests
Requires-Dist: PyYaml
Requires-Dist: python-gitlab
